<?xml version='1.0' encoding='utf-8'?>

<schemalist>
  <schema id='org.gnome.shell.extensions.custom-hot-corners.corner'>
    <key name='action' type='s'>
      <default>'disabled'</default>
    </key>
    <key name='command' type='s'>
      <default>''</default>
    </key>
    <key name='fullscreen' type='b'>
      <default>false</default>
    </key>
    <key name='barrier-size' type='i'>
      <default>20</default>
    </key>
    <key name='pressure-threshold' type='i'>
      <default>100</default>
    </key>
    <key name='workspace-index' type='i'>
      <default>1</default>
    </key>
  </schema>
  <schema id='org.gnome.shell.extensions.custom-hot-corners.misc'>
    <key name='fix11' type='b'>
      <default>true</default>
    </key>
    <key name='delay-start' type='b'>
      <default>false</default>
    </key>
    <key name='fullscreen-global' type='b'>
      <default>false</default>
    </key>
    <key name='panel-scroll' type='b'>
      <default>false</default>
    </key>
    <key name='ws-switch-ignore-last' type='b'>
      <default>false</default>
    </key>
    <key name='ws-switch-wrap' type='b'>
      <default>false</default>
    </key>
    <key name='ws-switch-indicator' type='b'>
      <default>false</default>
    </key>
    <key name='scroll-event-delay' type='i'>
      <default>50</default>
    </key>
  </schema>
</schemalist>
